setup.py
dttlz/__init__.py
dttlz/io.py
dttlz/model.py
dttlz.egg-info/PKG-INFO
dttlz.egg-info/SOURCES.txt
dttlz.egg-info/dependency_links.txt
dttlz.egg-info/not-zip-safe
dttlz.egg-info/top_level.txt