Metadata-Version: 1.1
Name: dttlz
Version: 0.0.1
Summary: Python data tools.
Home-page: http://github.com/asciimoo/dttlz
Author: Adam Tauber
Author-email: asciimoo@gmail.com
License: dttlz is free software: you can redistribute it and/or modify
